Workbook

Sheet Resumo
A1: VitaGesta: resumo para os slides
A2: ="Números calculados a partir da aba Premissas. Cenário da projeção: "&Premissas!B30&"."
A4: Indicador | B4: Valor | C4: Como é calculado
A5: Investimento na Fase 1 (MVP) | B5: =Premissas!D5 | C5: Média entre R$ 4.000 e R$ 6.000
A6: Investimento na Fase 2 (plataforma completa) | B6: =Premissas!D6 | C6: Média entre R$ 8.000 e R$ 12.000
A7: Custo mensal da operação | B7: =Premissas!D14 | C7: Hospedagem, domínio, manutenção e marketing
A8: Assinantes Pro que pagam a operação | B8: =ROUNDUP(Premissas!D14/Premissas!B18,0) | C8: Custo mensal ÷ preço do plano Pro, arredondado para cima
A9: Ou gestantes Premium que pagam a operação | B9: =ROUNDUP(Premissas!D14/Premissas!B17,0) | C9: Custo mensal ÷ preço do Premium, arredondado para cima
A10: Receita no mês 12 | B10: ='Projeção 12 meses'!E16 | C10: Receita do último mês da projeção
A11: Receita total em 12 meses | B11: ='Projeção 12 meses'!E17 | C11: Soma da receita dos 12 meses
A12: Resultado acumulado em 12 meses | B12: ='Projeção 12 meses'!H16 | C12: Receita menos custos, já descontado o investimento da Fase 1
A13: Mês em que a receita cobre o custo | B13: =IFERROR(MATCH(1,'Projeção 12 meses'!I5:I16,0),"Depois do mês 12") | C13: Primeiro mês com resultado do mês positivo
A14: Mês em que o investimento da Fase 1 volta | B14: =IFERROR(MATCH(1,'Projeção 12 meses'!J5:J16,0),"Depois do mês 12") | C14: Primeiro mês com resultado acumulado positivo
A17: Receita no mês 12 por cenário | B17: Pessimista | C17: Base | D17: Otimista
A18: Gestantes Premium | B18: =Premissas!B24*Premissas!$B$17 | C18: =Premissas!C24*Premissas!$B$17 | D18: =Premissas!D24*Premissas!$B$17
A19: Nutricionistas Pro | B19: =Premissas!B26*Premissas!$B$18 | C19: =Premissas!C26*Premissas!$B$18 | D19: =Premissas!D26*Premissas!$B$18
A20: Clínicas | B20: =Premissas!B28*Premissas!$B$19 | C20: =Premissas!C28*Premissas!$B$19 | D20: =Premissas!D28*Premissas!$B$19
A21: Receita mensal | B21: =SUM(B18:B20) | C21: =SUM(C18:C20) | D21: =SUM(D18:D20)
A22: Menos o custo mensal | B22: =-Premissas!$D$14 | C22: =-Premissas!$D$14 | D22: =-Premissas!$D$14
A23: Resultado mensal no mês 12 | B23: =B21+B22 | C23: =C21+C22 | D23: =D21+D22
A25: Princípio do modelo: a busca de profissionais ordena só por distância e avaliação. O plano pago dá ferramentas, nunca posição na lista.

Sheet Premissas
A1: VitaGesta: premissas de custos e receita
A2: Células em azul são editáveis. Em amarelo, o cenário usado na projeção. Valores em reais (R$).
A4: Investimento inicial | B4: Mínimo (R$) | C4: Máximo (R$) | D4: Valor usado (R$) | E4: Fonte
A5: Fase 1: MVP (site, calculadora, painel) | B5: 4000 | C5: 6000 | D5: =AVERAGE(B5:C5) | E5: Pesquisa de mercado do grupo, Goiânia, 2026
A6: Fase 2: plataforma completa (contas, agenda, app) | B6: 8000 | C6: 12000 | D6: =AVERAGE(B6:C6) | E6: Pesquisa de mercado do grupo, Goiânia, 2026
A7: Total do investimento | D7: =SUM(D5:D6) | E7: Valor usado = média entre mínimo e máximo
A9: Custo mensal da operação | B9: Quantidade | C9: Valor unitário (R$) | D9: Total por mês (R$) | E9: Fonte
A10: Hospedagem (Hostinger, PHP + MySQL) | B10: 1 | C10: 150 | D10: =B10*C10 | E10: Faixa pesquisada: R$ 50 a 300 por mês
A11: Domínio .com.br (R$ 70 por ano, rateado) | B11: 1 | C11: =70/12 | D11: =B11*C11 | E11: Faixa pesquisada: R$ 40 a 100 por ano
A12: Manutenção e suporte técnico (horas de freela) | B12: 6 | C12: 100 | D12: =B12*C12 | E12: Faixa pesquisada: R$ 80 a 120 por hora
A13: Marketing digital (anúncios e redes sociais) | B13: 1 | C13: 200 | D13: =B13*C13 | E13: Hipótese do grupo
A14: Custo mensal total | D14: =SUM(D10:D13) | E14: A pesquisa do grupo estimou R$ 800 a 1.200 por mês
A16: Preços (por mês) | B16: Preço (R$) | E16: Fonte
A17: Gestante Premium | B17: 14.9 | E17: Modelo de receita definido pelo grupo
A18: Nutricionista Pro | B18: 79 | E18: Modelo de receita definido pelo grupo
A19: Clínica (até 5 profissionais) | B19: 199 | E19: Modelo de receita definido pelo grupo
A20: Gestante Essencial e Nutricionista Básico são gratuitos e não entram na receita.
A22: Assinantes pagantes (hipótese) | B22: Pessimista | C22: Base | D22: Otimista | E22: Observação
A23: Gestantes Premium no mês 1 | B23: 5 | C23: 10 | D23: 20 | E23: Hipótese do grupo; cresce em linha reta do mês 1 ao mês 12
A24: Gestantes Premium no mês 12 | B24: 40 | C24: 120 | D24: 300 | E24: Hipótese do grupo; cresce em linha reta do mês 1 ao mês 12
A25: Nutricionistas Pro no mês 1 | B25: 2 | C25: 4 | D25: 6 | E25: Hipótese do grupo; cresce em linha reta do mês 1 ao mês 12
A26: Nutricionistas Pro no mês 12 | B26: 12 | C26: 25 | D26: 50 | E26: Hipótese do grupo; cresce em linha reta do mês 1 ao mês 12
A27: Clínicas no mês 1 | B27: 0 | C27: 0 | D27: 1 | E27: Hipótese do grupo; cresce em linha reta do mês 1 ao mês 12
A28: Clínicas no mês 12 | B28: 1 | C28: 3 | D28: 6 | E28: Hipótese do grupo; cresce em linha reta do mês 1 ao mês 12
A30: Cenário usado na projeção | B30: Base | C30: =MATCH(B30,B22:D22,0) | D30: ← coluna do cenário (1 a 3)

Sheet Projeção 12 meses
A1: Projeção de 12 meses
A2: ="Cenário: "&Premissas!B30&". Assinantes crescem em linha reta entre o mês 1 e o mês 12. Resultado acumulado parte do investimento da Fase 1."
A4: Mês | B4: Gestantes Premium | C4: Nutricionistas Pro | D4: Clínicas | E4: Receita (R$) | F4: Custo (R$) | G4: Resultado do mês (R$) | H4: Resultado acumulado (R$) | I4: Mês se paga? (1 = sim) | J4: Investimento recuperado? (1 = sim)
A5: 1 | B5: =ROUND(INDEX(Premissas!$B$23:$D$23,Premissas!$C$30)+(INDEX(Premissas!$B$24:$D$24,Premissas!$C$30)-INDEX(Premissas!$B$23:$D$23,Premissas!$C$30))*(A5-1)/11,0) | C5: =ROUND(INDEX(Premissas!$B$25:$D$25,Premissas!$C$30)+(INDEX(Premissas!$B$26:$D$26,Premissas!$C$30)-INDEX(Premissas!$B$25:$D$25,Premissas!$C$30))*(A5-1)/11,0) | D5: =ROUND(INDEX(Premissas!$B$27:$D$27,Premissas!$C$30)+(INDEX(Premissas!$B$28:$D$28,Premissas!$C$30)-INDEX(Premissas!$B$27:$D$27,Premissas!$C$30))*(A5-1)/11,0) | E5: =B5*Premissas!$B$17+C5*Premissas!$B$18+D5*Premissas!$B$19 | F5: =Premissas!$D$14 | G5: =E5-F5 | H5: =G5-Premissas!$D$5 | I5: =IF(G5>=0,1,0) | J5: =IF(H5>=0,1,0)
A6: 2 | B6: =ROUND(INDEX(Premissas!$B$23:$D$23,Premissas!$C$30)+(INDEX(Premissas!$B$24:$D$24,Premissas!$C$30)-INDEX(Premissas!$B$23:$D$23,Premissas!$C$30))*(A6-1)/11,0) | C6: =ROUND(INDEX(Premissas!$B$25:$D$25,Premissas!$C$30)+(INDEX(Premissas!$B$26:$D$26,Premissas!$C$30)-INDEX(Premissas!$B$25:$D$25,Premissas!$C$30))*(A6-1)/11,0) | D6: =ROUND(INDEX(Premissas!$B$27:$D$27,Premissas!$C$30)+(INDEX(Premissas!$B$28:$D$28,Premissas!$C$30)-INDEX(Premissas!$B$27:$D$27,Premissas!$C$30))*(A6-1)/11,0) | E6: =B6*Premissas!$B$17+C6*Premissas!$B$18+D6*Premissas!$B$19 | F6: =Premissas!$D$14 | G6: =E6-F6 | H6: =H5+G6 | I6: =IF(G6>=0,1,0) | J6: =IF(H6>=0,1,0)
A7: 3 | B7: =ROUND(INDEX(Premissas!$B$23:$D$23,Premissas!$C$30)+(INDEX(Premissas!$B$24:$D$24,Premissas!$C$30)-INDEX(Premissas!$B$23:$D$23,Premissas!$C$30))*(A7-1)/11,0) | C7: =ROUND(INDEX(Premissas!$B$25:$D$25,Premissas!$C$30)+(INDEX(Premissas!$B$26:$D$26,Premissas!$C$30)-INDEX(Premissas!$B$25:$D$25,Premissas!$C$30))*(A7-1)/11,0) | D7: =ROUND(INDEX(Premissas!$B$27:$D$27,Premissas!$C$30)+(INDEX(Premissas!$B$28:$D$28,Premissas!$C$30)-INDEX(Premissas!$B$27:$D$27,Premissas!$C$30))*(A7-1)/11,0) | E7: =B7*Premissas!$B$17+C7*Premissas!$B$18+D7*Premissas!$B$19 | F7: =Premissas!$D$14 | G7: =E7-F7 | H7: =H6+G7 | I7: =IF(G7>=0,1,0) | J7: =IF(H7>=0,1,0)
A8: 4 | B8: =ROUND(INDEX(Premissas!$B$23:$D$23,Premissas!$C$30)+(INDEX(Premissas!$B$24:$D$24,Premissas!$C$30)-INDEX(Premissas!$B$23:$D$23,Premissas!$C$30))*(A8-1)/11,0) | C8: =ROUND(INDEX(Premissas!$B$25:$D$25,Premissas!$C$30)+(INDEX(Premissas!$B$26:$D$26,Premissas!$C$30)-INDEX(Premissas!$B$25:$D$25,Premissas!$C$30))*(A8-1)/11,0) | D8: =ROUND(INDEX(Premissas!$B$27:$D$27,Premissas!$C$30)+(INDEX(Premissas!$B$28:$D$28,Premissas!$C$30)-INDEX(Premissas!$B$27:$D$27,Premissas!$C$30))*(A8-1)/11,0) | E8: =B8*Premissas!$B$17+C8*Premissas!$B$18+D8*Premissas!$B$19 | F8: =Premissas!$D$14 | G8: =E8-F8 | H8: =H7+G8 | I8: =IF(G8>=0,1,0) | J8: =IF(H8>=0,1,0)
A9: 5 | B9: =ROUND(INDEX(Premissas!$B$23:$D$23,Premissas!$C$30)+(INDEX(Premissas!$B$24:$D$24,Premissas!$C$30)-INDEX(Premissas!$B$23:$D$23,Premissas!$C$30))*(A9-1)/11,0) | C9: =ROUND(INDEX(Premissas!$B$25:$D$25,Premissas!$C$30)+(INDEX(Premissas!$B$26:$D$26,Premissas!$C$30)-INDEX(Premissas!$B$25:$D$25,Premissas!$C$30))*(A9-1)/11,0) | D9: =ROUND(INDEX(Premissas!$B$27:$D$27,Premissas!$C$30)+(INDEX(Premissas!$B$28:$D$28,Premissas!$C$30)-INDEX(Premissas!$B$27:$D$27,Premissas!$C$30))*(A9-1)/11,0) | E9: =B9*Premissas!$B$17+C9*Premissas!$B$18+D9*Premissas!$B$19 | F9: =Premissas!$D$14 | G9: =E9-F9 | H9: =H8+G9 | I9: =IF(G9>=0,1,0) | J9: =IF(H9>=0,1,0)
A10: 6 | B10: =ROUND(INDEX(Premissas!$B$23:$D$23,Premissas!$C$30)+(INDEX(Premissas!$B$24:$D$24,Premissas!$C$30)-INDEX(Premissas!$B$23:$D$23,Premissas!$C$30))*(A10-1)/11,0) | C10: =ROUND(INDEX(Premissas!$B$25:$D$25,Premissas!$C$30)+(INDEX(Premissas!$B$26:$D$26,Premissas!$C$30)-INDEX(Premissas!$B$25:$D$25,Premissas!$C$30))*(A10-1)/11,0) | D10: =ROUND(INDEX(Premissas!$B$27:$D$27,Premissas!$C$30)+(INDEX(Premissas!$B$28:$D$28,Premissas!$C$30)-INDEX(Premissas!$B$27:$D$27,Premissas!$C$30))*(A10-1)/11,0) | E10: =B10*Premissas!$B$17+C10*Premissas!$B$18+D10*Premissas!$B$19 | F10: =Premissas!$D$14 | G10: =E10-F10 | H10: =H9+G10 | I10: =IF(G10>=0,1,0) | J10: =IF(H10>=0,1,0)
A11: 7 | B11: =ROUND(INDEX(Premissas!$B$23:$D$23,Premissas!$C$30)+(INDEX(Premissas!$B$24:$D$24,Premissas!$C$30)-INDEX(Premissas!$B$23:$D$23,Premissas!$C$30))*(A11-1)/11,0) | C11: =ROUND(INDEX(Premissas!$B$25:$D$25,Premissas!$C$30)+(INDEX(Premissas!$B$26:$D$26,Premissas!$C$30)-INDEX(Premissas!$B$25:$D$25,Premissas!$C$30))*(A11-1)/11,0) | D11: =ROUND(INDEX(Premissas!$B$27:$D$27,Premissas!$C$30)+(INDEX(Premissas!$B$28:$D$28,Premissas!$C$30)-INDEX(Premissas!$B$27:$D$27,Premissas!$C$30))*(A11-1)/11,0) | E11: =B11*Premissas!$B$17+C11*Premissas!$B$18+D11*Premissas!$B$19 | F11: =Premissas!$D$14 | G11: =E11-F11 | H11: =H10+G11 | I11: =IF(G11>=0,1,0) | J11: =IF(H11>=0,1,0)
A12: 8 | B12: =ROUND(INDEX(Premissas!$B$23:$D$23,Premissas!$C$30)+(INDEX(Premissas!$B$24:$D$24,Premissas!$C$30)-INDEX(Premissas!$B$23:$D$23,Premissas!$C$30))*(A12-1)/11,0) | C12: =ROUND(INDEX(Premissas!$B$25:$D$25,Premissas!$C$30)+(INDEX(Premissas!$B$26:$D$26,Premissas!$C$30)-INDEX(Premissas!$B$25:$D$25,Premissas!$C$30))*(A12-1)/11,0) | D12: =ROUND(INDEX(Premissas!$B$27:$D$27,Premissas!$C$30)+(INDEX(Premissas!$B$28:$D$28,Premissas!$C$30)-INDEX(Premissas!$B$27:$D$27,Premissas!$C$30))*(A12-1)/11,0) | E12: =B12*Premissas!$B$17+C12*Premissas!$B$18+D12*Premissas!$B$19 | F12: =Premissas!$D$14 | G12: =E12-F12 | H12: =H11+G12 | I12: =IF(G12>=0,1,0) | J12: =IF(H12>=0,1,0)
A13: 9 | B13: =ROUND(INDEX(Premissas!$B$23:$D$23,Premissas!$C$30)+(INDEX(Premissas!$B$24:$D$24,Premissas!$C$30)-INDEX(Premissas!$B$23:$D$23,Premissas!$C$30))*(A13-1)/11,0) | C13: =ROUND(INDEX(Premissas!$B$25:$D$25,Premissas!$C$30)+(INDEX(Premissas!$B$26:$D$26,Premissas!$C$30)-INDEX(Premissas!$B$25:$D$25,Premissas!$C$30))*(A13-1)/11,0) | D13: =ROUND(INDEX(Premissas!$B$27:$D$27,Premissas!$C$30)+(INDEX(Premissas!$B$28:$D$28,Premissas!$C$30)-INDEX(Premissas!$B$27:$D$27,Premissas!$C$30))*(A13-1)/11,0) | E13: =B13*Premissas!$B$17+C13*Premissas!$B$18+D13*Premissas!$B$19 | F13: =Premissas!$D$14 | G13: =E13-F13 | H13: =H12+G13 | I13: =IF(G13>=0,1,0) | J13: =IF(H13>=0,1,0)
A14: 10 | B14: =ROUND(INDEX(Premissas!$B$23:$D$23,Premissas!$C$30)+(INDEX(Premissas!$B$24:$D$24,Premissas!$C$30)-INDEX(Premissas!$B$23:$D$23,Premissas!$C$30))*(A14-1)/11,0) | C14: =ROUND(INDEX(Premissas!$B$25:$D$25,Premissas!$C$30)+(INDEX(Premissas!$B$26:$D$26,Premissas!$C$30)-INDEX(Premissas!$B$25:$D$25,Premissas!$C$30))*(A14-1)/11,0) | D14: =ROUND(INDEX(Premissas!$B$27:$D$27,Premissas!$C$30)+(INDEX(Premissas!$B$28:$D$28,Premissas!$C$30)-INDEX(Premissas!$B$27:$D$27,Premissas!$C$30))*(A14-1)/11,0) | E14: =B14*Premissas!$B$17+C14*Premissas!$B$18+D14*Premissas!$B$19 | F14: =Premissas!$D$14 | G14: =E14-F14 | H14: =H13+G14 | I14: =IF(G14>=0,1,0) | J14: =IF(H14>=0,1,0)
A15: 11 | B15: =ROUND(INDEX(Premissas!$B$23:$D$23,Premissas!$C$30)+(INDEX(Premissas!$B$24:$D$24,Premissas!$C$30)-INDEX(Premissas!$B$23:$D$23,Premissas!$C$30))*(A15-1)/11,0) | C15: =ROUND(INDEX(Premissas!$B$25:$D$25,Premissas!$C$30)+(INDEX(Premissas!$B$26:$D$26,Premissas!$C$30)-INDEX(Premissas!$B$25:$D$25,Premissas!$C$30))*(A15-1)/11,0) | D15: =ROUND(INDEX(Premissas!$B$27:$D$27,Premissas!$C$30)+(INDEX(Premissas!$B$28:$D$28,Premissas!$C$30)-INDEX(Premissas!$B$27:$D$27,Premissas!$C$30))*(A15-1)/11,0) | E15: =B15*Premissas!$B$17+C15*Premissas!$B$18+D15*Premissas!$B$19 | F15: =Premissas!$D$14 | G15: =E15-F15 | H15: =H14+G15 | I15: =IF(G15>=0,1,0) | J15: =IF(H15>=0,1,0)
A16: 12 | B16: =ROUND(INDEX(Premissas!$B$23:$D$23,Premissas!$C$30)+(INDEX(Premissas!$B$24:$D$24,Premissas!$C$30)-INDEX(Premissas!$B$23:$D$23,Premissas!$C$30))*(A16-1)/11,0) | C16: =ROUND(INDEX(Premissas!$B$25:$D$25,Premissas!$C$30)+(INDEX(Premissas!$B$26:$D$26,Premissas!$C$30)-INDEX(Premissas!$B$25:$D$25,Premissas!$C$30))*(A16-1)/11,0) | D16: =ROUND(INDEX(Premissas!$B$27:$D$27,Premissas!$C$30)+(INDEX(Premissas!$B$28:$D$28,Premissas!$C$30)-INDEX(Premissas!$B$27:$D$27,Premissas!$C$30))*(A16-1)/11,0) | E16: =B16*Premissas!$B$17+C16*Premissas!$B$18+D16*Premissas!$B$19 | F16: =Premissas!$D$14 | G16: =E16-F16 | H16: =H15+G16 | I16: =IF(G16>=0,1,0) | J16: =IF(H16>=0,1,0)
A17: Total 12 meses | E17: =SUM(E5:E16) | F17: =SUM(F5:F16) | G17: =SUM(G5:G16)

Sheet Fontes
A1: Fontes e observações
A3: Pesquisa de mercado feita pelo grupo em 2026, Goiânia: landing page R$ 1.500 a 3.500; site institucional R$ 1.500 a 8.000; freela R$ 80 a 120 por hora; domínio .com.br R$ 40 a 100 por ano; hospedagem R$ 50 a 300 por mês.
A4: Proposta do grupo para os slides: Fase 1 (MVP) R$ 4.000 a 6.000; Fase 2 (plataforma completa) mais R$ 8.000 a 12.000; custo mensal de R$ 800 a 1.200.
A5: Modelo de receita do grupo: gestante grátis ou Premium R$ 14,90 por mês; nutricionista Básico grátis, Pro R$ 79 por mês, Clínica R$ 199 por mês.
A6: Marketing digital (R$ 200 por mês) e os números de assinantes de cada cenário são hipóteses do grupo, não dados de mercado. Ajuste na aba Premissas.
A7: Não inclui impostos nem taxas de pagamento (cartão ou Pix). Para um plano de negócios completo, some essas despesas.
A8: Protótipo acadêmico do projeto Materno Infantil, disciplina de Economia e Marketing, Facunicamps.
